bda/__init__.py
bda/benchmark_analyzer.py
bda/dashboard.py
bda/delta_analyzer.py
bda/file_kit.py
bda/assets/styles.css
util/__init__.py
util/cli_kit.py
version/__init__.py
version/_version.py
cedarverse_bda-0.0.1.dist-info/LICENSE
cedarverse_bda-0.0.1.dist-info/METADATA
cedarverse_bda-0.0.1.dist-info/WHEEL
cedarverse_bda-0.0.1.dist-info/entry_points.txt
cedarverse_bda-0.0.1.dist-info/top_level.txt
cedarverse_bda-0.0.1.dist-info/RECORD
