Metadata-Version: 2.1
Name: cedarverse-bda
Version: 0.0.1
Summary: Interactive dashboard tool for analyzing differences between Aider benchmark runs
Author-email: Elifarley <elifarley@cedarverse.com>
License: Apache-2.0
Project-URL: Homepage, https://github.com/cedarverse/benchmark-delta-analysis
Project-URL: Documentation, https://github.com/cedarverse/benchmark-delta-analysis#readme
Project-URL: Repository, https://github.com/cedarverse/benchmark-delta-analysis.git
Project-URL: Bug Tracker, https://github.com/cedarverse/benchmark-delta-analysis/issues
Keywords: benchmark,testing,analysis,visualization,dashboard,comparison,aider
Classifier: Development Status :: 3 - Alpha
Classifier: Programming Language :: Python :: 3
Classifier: Programming Language :: Python :: 3.12
Classifier: License :: OSI Approved :: Apache Software License
Classifier: Operating System :: OS Independent
Classifier: Intended Audience :: Developers
Classifier: Topic :: Software Development :: Testing
Classifier: Topic :: Software Development :: Quality Assurance
Classifier: Topic :: Software Development :: Libraries :: Python Modules
Requires-Python: >=3.12
License-File: LICENSE
Requires-Dist: python-dotenv>=1.0.1
Requires-Dist: dash>=2.18.2
Requires-Dist: pandas>=2.2.2
Requires-Dist: statsmodels>=0.14.2
Provides-Extra: dev
Requires-Dist: pytest>=7.0; extra == "dev"
Requires-Dist: black>=22.0; extra == "dev"
Requires-Dist: isort>=5.0; extra == "dev"
Requires-Dist: flake8>=4.0; extra == "dev"
Requires-Dist: mypy>=0.900; extra == "dev"
Requires-Dist: coverage>=6.0; extra == "dev"
Requires-Dist: tox>=3.24; extra == "dev"
Requires-Dist: build>=1.2.2; extra == "dev"
Requires-Dist: setuptools-scm>=8.1.0; extra == "dev"
